projectlumina/__init__.py
projectlumina/api.py
projectlumina/worldeditor.py
projectlumina-1.0.1.dist-info/METADATA
projectlumina-1.0.1.dist-info/WHEEL
projectlumina-1.0.1.dist-info/entry_points.txt
projectlumina-1.0.1.dist-info/top_level.txt
projectlumina-1.0.1.dist-info/RECORD
