Metadata-Version: 2.1
Name: projectlumina
Version: 1.0.1
Summary: A Python library providing an API wrapper and tools to edit Minecraft Bedrock level.dat files for Project Lumina.
Home-page: https://github.com/riqvip/projectlumina.py
Author: riqvip
Author-email: riqvip@gmail.com
Classifier: Programming Language :: Python :: 3
Classifier: License :: OSI Approved :: MIT License
Classifier: Operating System :: OS Independent
Requires-Dist: requests
